copy_static_website/deploy/ftp/__init__.py
copy_static_website/deploy/ftp/main.py
copy_static_website/download/__init__.py
copy_static_website/download/main.py
copy_static_website/update_site_ftp/__init__.py
copy_static_website/update_site_ftp/main.py
copy_static_website/utils/__init__.py
copy_static_website/utils/main.py
copy_static_website-0.0.5.dist-info/LICENSE
copy_static_website-0.0.5.dist-info/WHEEL
copy_static_website-0.0.5.dist-info/METADATA
copy_static_website-0.0.5.dist-info/RECORD
